Workbook

Sheet Sales_Data
A1: Order_ID | B1: Order_Date | C1: Customer_Name | D1: Segment | E1: Region | F1: Product_ID | G1: Product_Name_Lookup | H1: Units | I1: Unit_Price | J1: Gross_Revenue | K1: Discount_Pct | L1: Discount_Amt | M1: Net_Revenue | N1: Cost_of_Goods | O1: Net_Profit | P1: Profit_Margin
A2: ORD-2025-001 | B2: 2025-01-07 | C2: Monsoon Capital Advisors | D2: Corporate | E2: East | F2: PRD-001 | G2: =INDEX(Lookup_Table!:, MATCH(F2, Lookup_Table!:, 0)) | H2: 12 | I2: 45000 | J2: =H2*I2 | K2: 0.1 | L2: =J2*K2 | M2: =J2-L2 | N2: =ROUND(H2*I2*0.65, 2) | O2: =M2-N2 | P2: =O2/M2
A3: ORD-2025-002 | B3: 2025-02-05 | C3: Rohit Verma | D3: Consumer | E3: South | F3: PRD-002 | G3: =INDEX(Lookup_Table!:, MATCH(F3, Lookup_Table!:, 0)) | H3: 12 | I3: 25000 | J3: =H3*I3 | K3: 0 | L3: =J3*K3 | M3: =J3-L3 | N3: =ROUND(H3*I3*0.55, 2) | O3: =M3-N3 | P3: =O3/M3
A4: ORD-2025-003 | B4: 2025-05-20 | C4: Monsoon Capital Advisors | D4: Corporate | E4: East | F4: PRD-006 | G4: =INDEX(Lookup_Table!:, MATCH(F4, Lookup_Table!:, 0)) | H4: 2 | I4: 5000 | J4: =H4*I4 | K4: 0.15 | L4: =J4*K4 | M4: =J4-L4 | N4: =ROUND(H4*I4*0.40, 2) | O4: =M4-N4 | P4: =O4/M4
A5: ORD-2025-004 | B5: 2025-01-24 | C5: Apex Wealth Advisors | D5: Corporate | E5: North | F5: PRD-001 | G5: =INDEX(Lookup_Table!:, MATCH(F5, Lookup_Table!:, 0)) | H5: 4 | I5: 45000 | J5: =H5*I5 | K5: 0.05 | L5: =J5*K5 | M5: =J5-L5 | N5: =ROUND(H5*I5*0.65, 2) | O5: =M5-N5 | P5: =O5/M5
A6: ORD-2025-005 | B6: 2025-01-07 | C6: Quantum Global Funds | D6: Corporate | E6: West | F6: PRD-005 | G6: =INDEX(Lookup_Table!:, MATCH(F6, Lookup_Table!:, 0)) | H6: 9 | I6: 15000 | J6: =H6*I6 | K6: 0.05 | L6: =J6*K6 | M6: =J6-L6 | N6: =ROUND(H6*I6*0.50, 2) | O6: =M6-N6 | P6: =O6/M6
A7: ORD-2025-006 | B7: 2025-06-29 | C7: Rajesh Agarwal | D7: Consumer | E7: North | F7: PRD-006 | G7: =INDEX(Lookup_Table!:, MATCH(F7, Lookup_Table!:, 0)) | H7: 9 | I7: 5000 | J7: =H7*I7 | K7: 0.15 | L7: =J7*K7 | M7: =J7-L7 | N7: =ROUND(H7*I7*0.40, 2) | O7: =M7-N7 | P7: =O7/M7
A8: ORD-2025-007 | B8: 2025-05-31 | C8: Rohit Verma | D8: Consumer | E8: South | F8: PRD-004 | G8: =INDEX(Lookup_Table!:, MATCH(F8, Lookup_Table!:, 0)) | H8: 5 | I8: 20000 | J8: =H8*I8 | K8: 0 | L8: =J8*K8 | M8: =J8-L8 | N8: =ROUND(H8*I8*0.70, 2) | O8: =M8-N8 | P8: =O8/M8
A9: ORD-2025-008 | B9: 2025-06-28 | C9: Bengaluru Quant Desk | D9: FinTech Pro | E9: South | F9: PRD-002 | G9: =INDEX(Lookup_Table!:, MATCH(F9, Lookup_Table!:, 0)) | H9: 7 | I9: 25000 | J9: =H9*I9 | K9: 0.1 | L9: =J9*K9 | M9: =J9-L9 | N9: =ROUND(H9*I9*0.55, 2) | O9: =M9-N9 | P9: =O9/M9
A10: ORD-2025-009 | B10: 2025-02-25 | C10: Starlight Finvest | D10: FinTech Pro | E10: West | F10: PRD-002 | G10: =INDEX(Lookup_Table!:, MATCH(F10, Lookup_Table!:, 0)) | H10: 6 | I10: 25000 | J10: =H10*I10 | K10: 0 | L10: =J10*K10 | M10: =J10-L10 | N10: =ROUND(H10*I10*0.55, 2) | O10: =M10-N10 | P10: =O10/M10
A11: ORD-2025-010 | B11: 2025-01-25 | C11: Zenith Capital | D11: Corporate | E11: West | F11: PRD-004 | G11: =INDEX(Lookup_Table!:, MATCH(F11, Lookup_Table!:, 0)) | H11: 6 | I11: 20000 | J11: =H11*I11 | K11: 0.1 | L11: =J11*K11 | M11: =J11-L11 | N11: =ROUND(H11*I11*0.70, 2) | O11: =M11-N11 | P11: =O11/M11
A12: ORD-2025-011 | B12: 2025-01-12 | C12: Vikas Singhania | D12: Consumer | E12: East | F12: PRD-003 | G12: =INDEX(Lookup_Table!:, MATCH(F12, Lookup_Table!:, 0)) | H12: 12 | I12: 35000 | J12: =H12*I12 | K12: 0.15 | L12: =J12*K12 | M12: =J12-L12 | N12: =ROUND(H12*I12*0.60, 2) | O12: =M12-N12 | P12: =O12/M12
A13: ORD-2025-012 | B13: 2025-04-07 | C13: Quantum Global Funds | D13: Corporate | E13: West | F13: PRD-001 | G13: =INDEX(Lookup_Table!:, MATCH(F13, Lookup_Table!:, 0)) | H13: 2 | I13: 45000 | J13: =H13*I13 | K13: 0.1 | L13: =J13*K13 | M13: =J13-L13 | N13: =ROUND(H13*I13*0.65, 2) | O13: =M13-N13 | P13: =O13/M13
A14: ORD-2025-013 | B14: 2025-06-08 | C14: Mumbai High-Tech Assets | D14: Corporate | E14: West | F14: PRD-006 | G14: =INDEX(Lookup_Table!:, MATCH(F14, Lookup_Table!:, 0)) | H14: 6 | I14: 5000 | J14: =H14*I14 | K14: 0.05 | L14: =J14*K14 | M14: =J14-L14 | N14: =ROUND(H14*I14*0.40, 2) | O14: =M14-N14 | P14: =O14/M14
A15: ORD-2025-014 | B15: 2025-01-12 | C15: Rajesh Agarwal | D15: Consumer | E15: North | F15: PRD-001 | G15: =INDEX(Lookup_Table!:, MATCH(F15, Lookup_Table!:, 0)) | H15: 11 | I15: 45000 | J15: =H15*I15 | K15: 0.05 | L15: =J15*K15 | M15: =J15-L15 | N15: =ROUND(H15*I15*0.65, 2) | O15: =M15-N15 | P15: =O15/M15
A16: ORD-2025-015 | B16: 2025-01-21 | C16: Bengaluru Quant Desk | D16: FinTech Pro | E16: South | F16: PRD-003 | G16: =INDEX(Lookup_Table!:, MATCH(F16, Lookup_Table!:, 0)) | H16: 4 | I16: 35000 | J16: =H16*I16 | K16: 0 | L16: =J16*K16 | M16: =J16-L16 | N16: =ROUND(H16*I16*0.60, 2) | O16: =M16-N16 | P16: =O16/M16
A17: ORD-2025-016 | B17: 2025-04-27 | C17: Ananya Deshmukh | D17: Consumer | E17: West | F17: PRD-003 | G17: =INDEX(Lookup_Table!:, MATCH(F17, Lookup_Table!:, 0)) | H17: 11 | I17: 35000 | J17: =H17*I17 | K17: 0.1 | L17: =J17*K17 | M17: =J17-L17 | N17: =ROUND(H17*I17*0.60, 2) | O17: =M17-N17 | P17: =O17/M17
A18: ORD-2025-017 | B18: 2025-04-01 | C18: Kavita Sharma | D18: Consumer | E18: North | F18: PRD-003 | G18: =INDEX(Lookup_Table!:, MATCH(F18, Lookup_Table!:, 0)) | H18: 4 | I18: 35000 | J18: =H18*I18 | K18: 0.1 | L18: =J18*K18 | M18: =J18-L18 | N18: =ROUND(H18*I18*0.60, 2) | O18: =M18-N18 | P18: =O18/M18
A19: ORD-2025-018 | B19: 2025-06-15 | C19: Rajesh Agarwal | D19: Consumer | E19: North | F19: PRD-006 | G19: =INDEX(Lookup_Table!:, MATCH(F19, Lookup_Table!:, 0)) | H19: 2 | I19: 5000 | J19: =H19*I19 | K19: 0.05 | L19: =J19*K19 | M19: =J19-L19 | N19: =ROUND(H19*I19*0.40, 2) | O19: =M19-N19 | P19: =O19/M19
A20: ORD-2025-019 | B20: 2025-03-04 | C20: Quantum Global Funds | D20: Corporate | E20: West | F20: PRD-006 | G20: =INDEX(Lookup_Table!:, MATCH(F20, Lookup_Table!:, 0)) | H20: 3 | I20: 5000 | J20: =H20*I20 | K20: 0.15 | L20: =J20*K20 | M20: =J20-L20 | N20: =ROUND(H20*I20*0.40, 2) | O20: =M20-N20 | P20: =O20/M20
A21: ORD-2025-020 | B21: 2025-06-13 | C21: Ananya Deshmukh | D21: Consumer | E21: West | F21: PRD-003 | G21: =INDEX(Lookup_Table!:, MATCH(F21, Lookup_Table!:, 0)) | H21: 12 | I21: 35000 | J21: =H21*I21 | K21: 0.05 | L21: =J21*K21 | M21: =J21-L21 | N21: =ROUND(H21*I21*0.60, 2) | O21: =M21-N21 | P21: =O21/M21
A22: ORD-2025-021 | B22: 2025-01-15 | C22: Monsoon Capital Advisors | D22: Corporate | E22: East | F22: PRD-003 | G22: =INDEX(Lookup_Table!:, MATCH(F22, Lookup_Table!:, 0)) | H22: 4 | I22: 35000 | J22: =H22*I22 | K22: 0 | L22: =J22*K22 | M22: =J22-L22 | N22: =ROUND(H22*I22*0.60, 2) | O22: =M22-N22 | P22: =O22/M22
A23: ORD-2025-022 | B23: 2025-04-13 | C23: Bengaluru Quant Desk | D23: FinTech Pro | E23: South | F23: PRD-003 | G23: =INDEX(Lookup_Table!:, MATCH(F23, Lookup_Table!:, 0)) | H23: 5 | I23: 35000 | J23: =H23*I23 | K23: 0 | L23: =J23*K23 | M23: =J23-L23 | N23: =ROUND(H23*I23*0.60, 2) | O23: =M23-N23 | P23: =O23/M23
A24: ORD-2025-023 | B24: 2025-03-22 | C24: Rohit Verma | D24: Consumer | E24: South | F24: PRD-005 | G24: =INDEX(Lookup_Table!:, MATCH(F24, Lookup_Table!:, 0)) | H24: 4 | I24: 15000 | J24: =H24*I24 | K24: 0.15 | L24: =J24*K24 | M24: =J24-L24 | N24: =ROUND(H24*I24*0.50, 2) | O24: =M24-N24 | P24: =O24/M24
A25: ORD-2025-024 | B25: 2025-04-28 | C25: Ananya Deshmukh | D25: Consumer | E25: West | F25: PRD-006 | G25: =INDEX(Lookup_Table!:, MATCH(F25, Lookup_Table!:, 0)) | H25: 3 | I25: 5000 | J25: =H25*I25 | K25: 0.1 | L25: =J25*K25 | M25: =J25-L25 | N25: =ROUND(H25*I25*0.40, 2) | O25: =M25-N25 | P25: =O25/M25
A26: ORD-2025-025 | B26: 2025-05-24 | C26: Kavita Sharma | D26: Consumer | E26: North | F26: PRD-002 | G26: =INDEX(Lookup_Table!:, MATCH(F26, Lookup_Table!:, 0)) | H26: 9 | I26: 25000 | J26: =H26*I26 | K26: 0.1 | L26: =J26*K26 | M26: =J26-L26 | N26: =ROUND(H26*I26*0.55, 2) | O26: =M26-N26 | P26: =O26/M26
A27: ORD-2025-026 | B27: 2025-04-20 | C27: Rajesh Agarwal | D27: Consumer | E27: North | F27: PRD-005 | G27: =INDEX(Lookup_Table!:, MATCH(F27, Lookup_Table!:, 0)) | H27: 10 | I27: 15000 | J27: =H27*I27 | K27: 0.15 | L27: =J27*K27 | M27: =J27-L27 | N27: =ROUND(H27*I27*0.50, 2) | O27: =M27-N27 | P27: =O27/M27
A28: ORD-2025-027 | B28: 2025-02-05 | C28: Nexus Algo Labs | D28: FinTech Pro | E28: South | F28: PRD-002 | G28: =INDEX(Lookup_Table!:, MATCH(F28, Lookup_Table!:, 0)) | H28: 9 | I28: 25000 | J28: =H28*I28 | K28: 0.15 | L28: =J28*K28 | M28: =J28-L28 | N28: =ROUND(H28*I28*0.55, 2) | O28: =M28-N28 | P28: =O28/M28
A29: ORD-2025-028 | B29: 2025-01-29 | C29: Zenith Capital | D29: Corporate | E29: West | F29: PRD-001 | G29: =INDEX(Lookup_Table!:, MATCH(F29, Lookup_Table!:, 0)) | H29: 3 | I29: 45000 | J29: =H29*I29 | K29: 0.05 | L29: =J29*K29 | M29: =J29-L29 | N29: =ROUND(H29*I29*0.65, 2) | O29: =M29-N29 | P29: =O29/M29
A30: ORD-2025-029 | B30: 2025-04-19 | C30: Bengaluru Quant Desk | D30: FinTech Pro | E30: South | F30: PRD-006 | G30: =INDEX(Lookup_Table!:, MATCH(F30, Lookup_Table!:, 0)) | H30: 10 | I30: 5000 | J30: =H30*I30 | K30: 0 | L30: =J30*K30 | M30: =J30-L30 | N30: =ROUND(H30*I30*0.40, 2) | O30: =M30-N30 | P30: =O30/M30
A31: ORD-2025-030 | B31: 2025-06-02 | C31: Ananya Deshmukh | D31: Consumer | E31: West | F31: PRD-004 | G31: =INDEX(Lookup_Table!:, MATCH(F31, Lookup_Table!:, 0)) | H31: 8 | I31: 20000 | J31: =H31*I31 | K31: 0.1 | L31: =J31*K31 | M31: =J31-L31 | N31: =ROUND(H31*I31*0.70, 2) | O31: =M31-N31 | P31: =O31/M31
A32: ORD-2025-031 | B32: 2025-06-24 | C32: Quantum Global Funds | D32: Corporate | E32: West | F32: PRD-001 | G32: =INDEX(Lookup_Table!:, MATCH(F32, Lookup_Table!:, 0)) | H32: 12 | I32: 45000 | J32: =H32*I32 | K32: 0 | L32: =J32*K32 | M32: =J32-L32 | N32: =ROUND(H32*I32*0.65, 2) | O32: =M32-N32 | P32: =O32/M32
A33: ORD-2025-032 | B33: 2025-03-10 | C33: Monsoon Capital Advisors | D33: Corporate | E33: East | F33: PRD-005 | G33: =INDEX(Lookup_Table!:, MATCH(F33, Lookup_Table!:, 0)) | H33: 11 | I33: 15000 | J33: =H33*I33 | K33: 0.1 | L33: =J33*K33 | M33: =J33-L33 | N33: =ROUND(H33*I33*0.50, 2) | O33: =M33-N33 | P33: =O33/M33
A34: ORD-2025-033 | B34: 2025-04-22 | C34: Zenith Capital | D34: Corporate | E34: West | F34: PRD-003 | G34: =INDEX(Lookup_Table!:, MATCH(F34, Lookup_Table!:, 0)) | H34: 3 | I34: 35000 | J34: =H34*I34 | K34: 0.15 | L34: =J34*K34 | M34: =J34-L34 | N34: =ROUND(H34*I34*0.60, 2) | O34: =M34-N34 | P34: =O34/M34
A35: ORD-2025-034 | B35: 2025-03-09 | C35: Apex Wealth Advisors | D35: Corporate | E35: North | F35: PRD-006 | G35: =INDEX(Lookup_Table!:, MATCH(F35, Lookup_Table!:, 0)) | H35: 9 | I35: 5000 | J35: =H35*I35 | K35: 0.05 | L35: =J35*K35 | M35: =J35-L35 | N35: =ROUND(H35*I35*0.40, 2) | O35: =M35-N35 | P35: =O35/M35
A36: ORD-2025-035 | B36: 2025-06-10 | C36: Quantum Global Funds | D36: Corporate | E36: West | F36: PRD-001 | G36: =INDEX(Lookup_Table!:, MATCH(F36, Lookup_Table!:, 0)) | H36: 5 | I36: 45000 | J36: =H36*I36 | K36: 0.05 | L36: =J36*K36 | M36: =J36-L36 | N36: =ROUND(H36*I36*0.65, 2) | O36: =M36-N36 | P36: =O36/M36
A37: ORD-2025-036 | B37: 2025-02-11 | C37: Kavita Sharma | D37: Consumer | E37: North | F37: PRD-003 | G37: =INDEX(Lookup_Table!:, MATCH(F37, Lookup_Table!:, 0)) | H37: 9 | I37: 35000 | J37: =H37*I37 | K37: 0 | L37: =J37*K37 | M37: =J37-L37 | N37: =ROUND(H37*I37*0.60, 2) | O37: =M37-N37 | P37: =O37/M37
A38: ORD-2025-037 | B38: 2025-05-06 | C38: Vikas Singhania | D38: Consumer | E38: East | F38: PRD-003 | G38: =INDEX(Lookup_Table!:, MATCH(F38, Lookup_Table!:, 0)) | H38: 1 | I38: 35000 | J38: =H38*I38 | K38: 0 | L38: =J38*K38 | M38: =J38-L38 | N38: =ROUND(H38*I38*0.60, 2) | O38: =M38-N38 | P38: =O38/M38
A39: ORD-2025-038 | B39: 2025-03-20 | C39: Kolkata Smart Equity | D39: Corporate | E39: East | F39: PRD-003 | G39: =INDEX(Lookup_Table!:, MATCH(F39, Lookup_Table!:, 0)) | H39: 4 | I39: 35000 | J39: =H39*I39 | K39: 0 | L39: =J39*K39 | M39: =J39-L39 | N39: =ROUND(H39*I39*0.60, 2) | O39: =M39-N39 | P39: =O39/M39
A40: ORD-2025-039 | B40: 2025-01-21 | C40: Rohit Verma | D40: Consumer | E40: South | F40: PRD-005 | G40: =INDEX(Lookup_Table!:, MATCH(F40, Lookup_Table!:, 0)) | H40: 2 | I40: 15000 | J40: =H40*I40 | K40: 0.15 | L40: =J40*K40 | M40: =J40-L40 | N40: =ROUND(H40*I40*0.50, 2) | O40: =M40-N40 | P40: =O40/M40
A41: ORD-2025-040 | B41: 2025-05-17 | C41: Mumbai High-Tech Assets | D41: Corporate | E41: West | F41: PRD-001 | G41: =INDEX(Lookup_Table!:, MATCH(F41, Lookup_Table!:, 0)) | H41: 3 | I41: 45000 | J41: =H41*I41 | K41: 0.05 | L41: =J41*K41 | M41: =J41-L41 | N41: =ROUND(H41*I41*0.65, 2) | O41: =M41-N41 | P41: =O41/M41
A42: ORD-2025-041 | B42: 2025-05-21 | C42: Monsoon Capital Advisors | D42: Corporate | E42: East | F42: PRD-004 | G42: =INDEX(Lookup_Table!:, MATCH(F42, Lookup_Table!:, 0)) | H42: 3 | I42: 20000 | J42: =H42*I42 | K42: 0.1 | L42: =J42*K42 | M42: =J42-L42 | N42: =ROUND(H42*I42*0.70, 2) | O42: =M42-N42 | P42: =O42/M42
A43: ORD-2025-042 | B43: 2025-04-19 | C43: Quantum Global Funds | D43: Corporate | E43: West | F43: PRD-005 | G43: =INDEX(Lookup_Table!:, MATCH(F43, Lookup_Table!:, 0)) | H43: 4 | I43: 15000 | J43: =H43*I43 | K43: 0.05 | L43: =J43*K43 | M43: =J43-L43 | N43: =ROUND(H43*I43*0.50, 2) | O43: =M43-N43 | P43: =O43/M43
A44: ORD-2025-043 | B44: 2025-04-13 | C44: Rajesh Agarwal | D44: Consumer | E44: North | F44: PRD-003 | G44: =INDEX(Lookup_Table!:, MATCH(F44, Lookup_Table!:, 0)) | H44: 11 | I44: 35000 | J44: =H44*I44 | K44: 0.1 | L44: =J44*K44 | M44: =J44-L44 | N44: =ROUND(H44*I44*0.60, 2) | O44: =M44-N44 | P44: =O44/M44
A45: ORD-2025-044 | B45: 2025-04-26 | C45: Pooja Nair | D45: Consumer | E45: South | F45: PRD-005 | G45: =INDEX(Lookup_Table!:, MATCH(F45, Lookup_Table!:, 0)) | H45: 2 | I45: 15000 | J45: =H45*I45 | K45: 0.05 | L45: =J45*K45 | M45: =J45-L45 | N45: =ROUND(H45*I45*0.50, 2) | O45: =M45-N45 | P45: =O45/M45
A46: ORD-2025-045 | B46: 2025-03-28 | C46: Rohit Verma | D46: Consumer | E46: South | F46: PRD-001 | G46: =INDEX(Lookup_Table!:, MATCH(F46, Lookup_Table!:, 0)) | H46: 1 | I46: 45000 | J46: =H46*I46 | K46: 0.05 | L46: =J46*K46 | M46: =J46-L46 | N46: =ROUND(H46*I46*0.65, 2) | O46: =M46-N46 | P46: =O46/M46
A47: ORD-2025-046 | B47: 2025-01-02 | C47: Vikas Singhania | D47: Consumer | E47: East | F47: PRD-002 | G47: =INDEX(Lookup_Table!:, MATCH(F47, Lookup_Table!:, 0)) | H47: 2 | I47: 25000 | J47: =H47*I47 | K47: 0 | L47: =J47*K47 | M47: =J47-L47 | N47: =ROUND(H47*I47*0.55, 2) | O47: =M47-N47 | P47: =O47/M47
A48: ORD-2025-047 | B48: 2025-01-09 | C48: Rohit Verma | D48: Consumer | E48: South | F48: PRD-001 | G48: =INDEX(Lookup_Table!:, MATCH(F48, Lookup_Table!:, 0)) | H48: 6 | I48: 45000 | J48: =H48*I48 | K48: 0 | L48: =J48*K48 | M48: =J48-L48 | N48: =ROUND(H48*I48*0.65, 2) | O48: =M48-N48 | P48: =O48/M48
A49: ORD-2025-048 | B49: 2025-03-13 | C49: Quantum Global Funds | D49: Corporate | E49: West | F49: PRD-002 | G49: =INDEX(Lookup_Table!:, MATCH(F49, Lookup_Table!:, 0)) | H49: 11 | I49: 25000 | J49: =H49*I49 | K49: 0.15 | L49: =J49*K49 | M49: =J49-L49 | N49: =ROUND(H49*I49*0.55, 2) | O49: =M49-N49 | P49: =O49/M49
A50: ORD-2025-049 | B50: 2025-02-03 | C50: Rohit Verma | D50: Consumer | E50: South | F50: PRD-005 | G50: =INDEX(Lookup_Table!:, MATCH(F50, Lookup_Table!:, 0)) | H50: 12 | I50: 15000 | J50: =H50*I50 | K50: 0.15 | L50: =J50*K50 | M50: =J50-L50 | N50: =ROUND(H50*I50*0.50, 2) | O50: =M50-N50 | P50: =O50/M50
A51: ORD-2025-050 | B51: 2025-04-15 | C51: Rohit Verma | D51: Consumer | E51: South | F51: PRD-004 | G51: =INDEX(Lookup_Table!:, MATCH(F51, Lookup_Table!:, 0)) | H51: 4 | I51: 20000 | J51: =H51*I51 | K51: 0 | L51: =J51*K51 | M51: =J51-L51 | N51: =ROUND(H51*I51*0.70, 2) | O51: =M51-N51 | P51: =O51/M51
A52: ORD-2025-051 | B52: 2025-04-21 | C52: Zenith Capital | D52: Corporate | E52: West | F52: PRD-006 | G52: =INDEX(Lookup_Table!:, MATCH(F52, Lookup_Table!:, 0)) | H52: 6 | I52: 5000 | J52: =H52*I52 | K52: 0.15 | L52: =J52*K52 | M52: =J52-L52 | N52: =ROUND(H52*I52*0.40, 2) | O52: =M52-N52 | P52: =O52/M52
A53: ORD-2025-052 | B53: 2025-01-14 | C53: Ananya Deshmukh | D53: Consumer | E53: West | F53: PRD-004 | G53: =INDEX(Lookup_Table!:, MATCH(F53, Lookup_Table!:, 0)) | H53: 11 | I53: 20000 | J53: =H53*I53 | K53: 0 | L53: =J53*K53 | M53: =J53-L53 | N53: =ROUND(H53*I53*0.70, 2) | O53: =M53-N53 | P53: =O53/M53
A54: ORD-2025-053 | B54: 2025-03-28 | C54: Apex Wealth Advisors | D54: Corporate | E54: North | F54: PRD-004 | G54: =INDEX(Lookup_Table!:, MATCH(F54, Lookup_Table!:, 0)) | H54: 2 | I54: 20000 | J54: =H54*I54 | K54: 0.05 | L54: =J54*K54 | M54: =J54-L54 | N54: =ROUND(H54*I54*0.70, 2) | O54: =M54-N54 | P54: =O54/M54
A55: ORD-2025-054 | B55: 2025-05-18 | C55: Rohit Verma | D55: Consumer | E55: South | F55: PRD-002 | G55: =INDEX(Lookup_Table!:, MATCH(F55, Lookup_Table!:, 0)) | H55: 8 | I55: 25000 | J55: =H55*I55 | K55: 0.05 | L55: =J55*K55 | M55: =J55-L55 | N55: =ROUND(H55*I55*0.55, 2) | O55: =M55-N55 | P55: =O55/M55
A56: ORD-2025-055 | B56: 2025-03-13 | C56: Ananya Deshmukh | D56: Consumer | E56: West | F56: PRD-002 | G56: =INDEX(Lookup_Table!:, MATCH(F56, Lookup_Table!:, 0)) | H56: 8 | I56: 25000 | J56: =H56*I56 | K56: 0.05 | L56: =J56*K56 | M56: =J56-L56 | N56: =ROUND(H56*I56*0.55, 2) | O56: =M56-N56 | P56: =O56/M56
A57: ORD-2025-056 | B57: 2025-04-24 | C57: Mumbai High-Tech Assets | D57: Corporate | E57: West | F57: PRD-001 | G57: =INDEX(Lookup_Table!:, MATCH(F57, Lookup_Table!:, 0)) | H57: 9 | I57: 45000 | J57: =H57*I57 | K57: 0 | L57: =J57*K57 | M57: =J57-L57 | N57: =ROUND(H57*I57*0.65, 2) | O57: =M57-N57 | P57: =O57/M57
A58: ORD-2025-057 | B58: 2025-05-19 | C58: Apex Wealth Advisors | D58: Corporate | E58: North | F58: PRD-006 | G58: =INDEX(Lookup_Table!:, MATCH(F58, Lookup_Table!:, 0)) | H58: 1 | I58: 5000 | J58: =H58*I58 | K58: 0 | L58: =J58*K58 | M58: =J58-L58 | N58: =ROUND(H58*I58*0.40, 2) | O58: =M58-N58 | P58: =O58/M58
A59: ORD-2025-058 | B59: 2025-02-12 | C59: Kolkata Smart Equity | D59: Corporate | E59: East | F59: PRD-002 | G59: =INDEX(Lookup_Table!:, MATCH(F59, Lookup_Table!:, 0)) | H59: 7 | I59: 25000 | J59: =H59*I59 | K59: 0.15 | L59: =J59*K59 | M59: =J59-L59 | N59: =ROUND(H59*I59*0.55, 2) | O59: =M59-N59 | P59: =O59/M59
A60: ORD-2025-059 | B60: 2025-04-13 | C60: Pooja Nair | D60: Consumer | E60: South | F60: PRD-002 | G60: =INDEX(Lookup_Table!:, MATCH(F60, Lookup_Table!:, 0)) | H60: 1 | I60: 25000 | J60: =H60*I60 | K60: 0.05 | L60: =J60*K60 | M60: =J60-L60 | N60: =ROUND(H60*I60*0.55, 2) | O60: =M60-N60 | P60: =O60/M60
A61: ORD-2025-060 | B61: 2025-04-10 | C61: Ananya Deshmukh | D61: Consumer | E61: West | F61: PRD-001 | G61: =INDEX(Lookup_Table!:, MATCH(F61, Lookup_Table!:, 0)) | H61: 5 | I61: 45000 | J61: =H61*I61 | K61: 0.15 | L61: =J61*K61 | M61: =J61-L61 | N61: =ROUND(H61*I61*0.65, 2) | O61: =M61-N61 | P61: =O61/M61

Sheet Lookup_Table
A1: Product_ID | B1: Category | C1: Product_Name | D1: Standard_Price | E1: Target_Margin | F1: Support_Tier
A2: PRD-001 | B2: FinTech Analytics | C2: Bluestock Pro Terminal | D2: 45000 | E2: 0.35 | F2: Premium 24/7
A3: PRD-002 | B3: API Solutions | C3: Real-Time Market Data Feed | D3: 25000 | E3: 0.45 | F3: Standard SLA
A4: PRD-003 | B4: Investment Research | C4: Algorithmic Strategy Suite | D4: 35000 | E4: 0.4 | F4: Premium 24/7
A5: PRD-004 | B5: Wealth Advisory | C5: Portfolio Risk Optimizer | D5: 20000 | E5: 0.3 | F5: Standard SLA
A6: PRD-005 | B6: Compliance & Tax | C6: Automated GST & Capital Gains Engine | D6: 15000 | E6: 0.5 | F6: Standard SLA
A7: PRD-006 | B7: Retail Subscriptions | C7: Investor Learning & Screener Pass | D7: 5000 | E7: 0.6 | F7: Community Support

Sheet Executive_Dashboard
B2: BLUESTOCK FINTECH — SALES & REVENUE PERFORMANCE DASHBOARD
B5: TOTAL GROSS REVENUE | E5: TOTAL NET REVENUE | H5: TOTAL NET PROFIT | K5: OVERALL PROFIT MARGIN
B6: =SUM(Sales_Data!J2:J61) | E6: =SUM(Sales_Data!M2:M61) | H6: =SUM(Sales_Data!O2:O61) | K6: =H6/E6
B9: Regional Revenue Breakdown | H9: Segment Performance
B10: Region | C10: Order Count | D10: Net Revenue | E10: Profit | F10: Margin % | H10: Customer Segment | I10: Orders | J10: Net Revenue | K10: Profit
B11: North | C11: =COUNTIF(Sales_Data!E2:E61, "North") | D11: =SUMIFS(Sales_Data!M2:M61, Sales_Data!E2:E61, "North") | E11: =SUMIFS(Sales_Data!O2:O61, Sales_Data!E2:E61, "North") | F11: =E11/D11 | H11: Corporate | I11: =COUNTIF(Sales_Data!D2:D61, "Corporate") | J11: =SUMIFS(Sales_Data!M2:M61, Sales_Data!D2:D61, "Corporate") | K11: =SUMIFS(Sales_Data!O2:O61, Sales_Data!D2:D61, "Corporate")
B12: South | C12: =COUNTIF(Sales_Data!E2:E61, "South") | D12: =SUMIFS(Sales_Data!M2:M61, Sales_Data!E2:E61, "South") | E12: =SUMIFS(Sales_Data!O2:O61, Sales_Data!E2:E61, "South") | F12: =E12/D12 | H12: FinTech Pro | I12: =COUNTIF(Sales_Data!D2:D61, "FinTech Pro") | J12: =SUMIFS(Sales_Data!M2:M61, Sales_Data!D2:D61, "FinTech Pro") | K12: =SUMIFS(Sales_Data!O2:O61, Sales_Data!D2:D61, "FinTech Pro")
B13: East | C13: =COUNTIF(Sales_Data!E2:E61, "East") | D13: =SUMIFS(Sales_Data!M2:M61, Sales_Data!E2:E61, "East") | E13: =SUMIFS(Sales_Data!O2:O61, Sales_Data!E2:E61, "East") | F13: =E13/D13 | H13: Consumer | I13: =COUNTIF(Sales_Data!D2:D61, "Consumer") | J13: =SUMIFS(Sales_Data!M2:M61, Sales_Data!D2:D61, "Consumer") | K13: =SUMIFS(Sales_Data!O2:O61, Sales_Data!D2:D61, "Consumer")
B14: West | C14: =COUNTIF(Sales_Data!E2:E61, "West") | D14: =SUMIFS(Sales_Data!M2:M61, Sales_Data!E2:E61, "West") | E14: =SUMIFS(Sales_Data!O2:O61, Sales_Data!E2:E61, "West") | F14: =E14/D14
B15: Total | C15: =SUM(C11:C14) | D15: =SUM(D11:D14) | E15: =SUM(E11:E14) | F15: =E15/D15

Sheet Pivot_Summaries
